devseeker/__init__.py
devseeker/applications/__init__.py
devseeker/applications/cli/__init__.py
devseeker/applications/cli/cli_agent.py
devseeker/applications/cli/collect.py
devseeker/applications/cli/file_selector.py
devseeker/applications/cli/learning.py
devseeker/applications/cli/main.py
devseeker/benchmark/__init__.py
devseeker/benchmark/__main__.py
devseeker/benchmark/bench_config.py
devseeker/benchmark/benchmarks/apps/load.py
devseeker/benchmark/benchmarks/apps/problem.py
devseeker/benchmark/benchmarks/apps/problems.py
devseeker/benchmark/benchmarks/gptme/load.py
devseeker/benchmark/benchmarks/load.py
devseeker/benchmark/benchmarks/mbpp/load.py
devseeker/benchmark/benchmarks/mbpp/problem.py
devseeker/benchmark/benchmarks/mbpp/problems.py
devseeker/benchmark/default_bench_config.toml
devseeker/benchmark/run.py
devseeker/benchmark/types.py
devseeker/core/__init__.py
devseeker/core/ai.py
devseeker/core/base_agent.py
devseeker/core/base_execution_env.py
devseeker/core/base_memory.py
devseeker/core/chat_to_files.py
devseeker/core/default/__init__.py
devseeker/core/default/constants.py
devseeker/core/default/disk_execution_env.py
devseeker/core/default/disk_memory.py
devseeker/core/default/file_store.py
devseeker/core/default/paths.py
devseeker/core/default/simple_agent.py
devseeker/core/default/steps.py
devseeker/core/diff.py
devseeker/core/files_dict.py
devseeker/core/git.py
devseeker/core/linting.py
devseeker/core/preprompts_holder.py
devseeker/core/project_config.py
devseeker/core/prompt.py
devseeker/core/token_usage.py
devseeker/core/version_manager.py
devseeker/preprompts/clarify
devseeker/preprompts/entrypoint
devseeker/preprompts/file_format
devseeker/preprompts/file_format_diff
devseeker/preprompts/file_format_fix
devseeker/preprompts/generate
devseeker/preprompts/improve
devseeker/preprompts/philosophy
devseeker/preprompts/roadmap
devseeker/tools/__init__.py
devseeker/tools/custom_steps.py
devseeker/tools/supported_languages.py
devseeker-0.0.5.dist-info/LICENSE
devseeker-0.0.5.dist-info/METADATA
devseeker-0.0.5.dist-info/WHEEL
devseeker-0.0.5.dist-info/entry_points.txt
devseeker-0.0.5.dist-info/RECORD
